projecttalos/__init__.py
projecttalos/data_preprocessing.py
projecttalos/models.py
projecttalos/nn_funcs/__init__.py
projecttalos/nn_funcs/activation_functions.py
projecttalos/nn_funcs/backward_prop.py
projecttalos/nn_funcs/forward_prop.py
projecttalos/nn_funcs/test.py
projecttalos-0.0.3.dist-info/LICENSE
projecttalos-0.0.3.dist-info/METADATA
projecttalos-0.0.3.dist-info/WHEEL
projecttalos-0.0.3.dist-info/top_level.txt
projecttalos-0.0.3.dist-info/RECORD
