Metadata-Version: 2.1
Name: projecttalos
Version: 0.0.3
Summary: A small Machine Learning package
Home-page: https://github.com/Xessen/ProjectTalos
Author: Şeyhmus Baskın
Author-email: seyhmusbaskin@yandex.com
License: UNKNOWN
Platform: UNKNOWN
Classifier: Programming Language :: Python :: 3
Classifier: License :: OSI Approved :: MIT License
Classifier: Operating System :: OS Independent
Requires-Python: >=3.3
Requires-Dist: numpy (>=1.15.0)
